CHANGES
LICENSE.txt
MANIFEST.in
README.rst
setup.cfg
setup.py
CuevanaLinks.egg-info/PKG-INFO
CuevanaLinks.egg-info/SOURCES.txt
CuevanaLinks.egg-info/dependency_links.txt
CuevanaLinks.egg-info/requires.txt
CuevanaLinks.egg-info/top_level.txt
bin/cuevanalinks
cuevanalinks/__init__.py
cuevanalinks/cuevanacli.py
tests/local/_box_1076.jpg
tests/local/_box_910.jpg
tests/local/_box_997.jpg
tests/local/_buscar_-q=a+non+existent+content-cat=titulo
tests/local/_buscar_-q=alexandre+rodrigues-cat=actor
tests/local/_buscar_-q=bielinsky-cat=director
tests/local/_buscar_-q=hamsterdam-cat=episodio
tests/local/_buscar_-q=matrix-cat=titulo
tests/local/_download_sub-file=s_sub_3309_ES.srt
tests/local/_download_sub-file=sub_997_ES.srt
tests/local/_peliculas_1049_cidade-de-deus_
tests/local/_peliculas_1076_amores-perros_
tests/local/_peliculas_232_el-aura_
tests/local/_peliculas_71_nueve-reinas_
tests/local/_peliculas_997_the-godfather_
tests/local/_player_source-id=1076
tests/local/_player_source-id=3309-tipo=s
tests/local/_player_source-id=997
tests/local/_rss_peliculas
tests/local/_rss_series
tests/local/_series
tests/local/_series_115_dexter_
tests/local/_series_1460_dummy
tests/local/_series_1619_dummy
tests/local/_series_1912_dummy
tests/local/_series_2833_dexter_pilot_
tests/local/_series_2834_dexter_crocodile_
tests/local/_series_2835_dexter_popping-cherry_
tests/local/_series_285_the-big-bang-theory_pilot_
tests/local/_series_2888_dexter_lets-give-the-boy-a-hand_
tests/local/_series_2893_dexter_love-american-style_
tests/local/_series_2901_dexter_do-you-take-dexter-morgan_
tests/local/_series_2912_dexter_our-father_
tests/local/_series_2934_dexter_return-to-sender_
tests/local/_series_2935_dexter_circle-of-friends_
tests/local/_series_2936_dexter_shrink-wrap_
tests/local/_series_2944_dexter_father-knows-best_
tests/local/_series_2945_dexter_seeing-red_
tests/local/_series_2947_dexter_truth-be-told_
tests/local/_series_2948_dexter_born-free_
tests/local/_series_2999_dexter_its-alive_
tests/local/_series_3001_dexter_see-through_
tests/local/_series_3088_the-wire_the-target_
tests/local/_series_3089_the-wire_the-detail_
