Metadata-Version: 1.0
Name: CuevanaLinks
Version: 0.5
Summary: A program to retrieve movies and series (or its links)                    from cuevana.tv
Home-page: https://bitbucket.org/tin_nqn/cuevanalinks
Author: Martín Gaitán
Author-email: gaitan@gmail.com
License: GNU GENERAL PUBLIC LICENCE v3.0 (see LICENCE.txt)
Platform: UNKNOWN
Classifier: Development Status :: 4 - Beta
Classifier: Environment :: Console
Classifier: Intended Audience :: End Users/Desktop
Classifier: License :: OSI Approved :: GNU General Public License (GPL)
Classifier: Natural Language :: English
Classifier: Operating System :: OS Independent
Classifier: Programming Language :: Python
Classifier: Topic :: Internet :: WWW/HTTP :: Dynamic Content
